pyslayer
