Metadata-Version: 1.0
Name: pyslayer
Version: 0.1.2
Summary: a python clone of dbslayer - JSON HTTP abstraction for DBAPI
Home-page: https://github.com/urielka/pyslayer
Author: Uriel Katz
Author-email: uriel.katz@gmail.com
License: MIT
Download-URL: https://github.com/urielka/pyslayer/downloads
Keywords: dbslayer json dbapi
Platform: UNKNOWN
